liblp/__init__.py
liblp/images.py
liblp/include/builder.py
liblp/include/liblp.py
liblp/include/metadata_format.py
liblp/include/partition_opener.py
liblp/liblp.py
liblp/partition_opener.py
liblp/partition_tools/lpunpack.py
liblp/reader.py
liblp/utility.py
liblp/writer.py
liblp-1.0.2.dist-info/entry_points.txt
liblp-1.0.2.dist-info/WHEEL
liblp-1.0.2.dist-info/METADATA
liblp-1.0.2.dist-info/RECORD
